ai_commit_and_readme/__init__.py
ai_commit_and_readme/cli.py
ai_commit_and_readme/constants.py
ai_commit_and_readme/logging_setup.py
ai_commit_and_readme/main.py
ai_commit_and_readme/prompt.md
ai_commit_and_readme/tools.py
ai_commit_and_readme-1.0.4.dist-info/METADATA
ai_commit_and_readme-1.0.4.dist-info/WHEEL
ai_commit_and_readme-1.0.4.dist-info/entry_points.txt
ai_commit_and_readme-1.0.4.dist-info/top_level.txt
ai_commit_and_readme-1.0.4.dist-info/RECORD
