Metadata-Version: 2.4
Name: ai_commit_and_readme
Version: 1.0.4
Summary: AI-powered README.md and commit message generation tool using OpenAI
Author-email: Oleksandr Kryklia <kryklia@gmail.com>
License-Expression: MIT
Project-URL: Homepage, https://github.com/auraz/ai_commit_and_readme
Project-URL: Bug Tracker, https://github.com/auraz/ai_commit_and_readme/issues
Project-URL: Documentation, https://github.com/auraz/ai_commit_and_readme/wiki
Classifier: Programming Language :: Python :: 3
Classifier: Operating System :: OS Independent
Classifier: Topic :: Software Development :: Documentation
Classifier: Topic :: Software Development :: Libraries :: Python Modules
Requires-Python: >=3.7
Requires-Dist: openai>=1.0.0
Requires-Dist: tiktoken>=0.5.1
Requires-Dist: rich>=13.0.0
Requires-Dist: pipetools>=0.1.0
